[{"line":2,"elements":[{"start_timestamp":"2023-06-14T15:44:09.885Z","line":5,"name":"User abandons first question","description":"","id":"3-out-of-4-strategy.-user-has-2-kbv-questions.-tests-are-run-against-the-kbv-stub.;user-abandons-first-question","type":"scenario","keyword":"Scenario","steps":[{"result":{"duration":1869742000,"status":"passed"},"line":6,"name":"user has the test-identity 168 in the form of a signed JWT string","match":{"arguments":[{"val":"168","offset":27}],"location":"uk.gov.di.ipv.cri.common.library.stepdefinitions.CommonSteps.userHasTheTestIdentityInTheFormOfASignedJWTString(int)"},"keyword":"Given "},{"result":{"duration":2453213000,"status":"passed"},"line":9,"name":"user sends a POST request to session end point","match":{"location":"uk.gov.di.ipv.cri.common.library.stepdefinitions.CommonSteps.userSendsAPostRequestToSessionEndpoint()"},"keyword":"When "},{"result":{"duration":2454000,"status":"passed"},"line":10,"name":"user gets a session-id","match":{"location":"uk.gov.di.ipv.cri.common.library.stepdefinitions.CommonSteps.userGetsASessionId()"},"keyword":"Then "},{"result":{"duration":12082739000,"status":"passed"},"line":13,"name":"user sends a GET request to question end point","match":{"location":"gov.uk.kbv.api.stepdefinitions.KbvSteps.user_sends_a_get_request_to_question_end_point()"},"keyword":"When "},{"result":{"duration":586000,"status":"passed"},"line":14,"name":"user gets status code 200","match":{"arguments":[{"val":"200","offset":22}],"location":"uk.gov.di.ipv.cri.common.library.stepdefinitions.CommonSteps.userGetsStatusCode(int)"},"keyword":"Then "},{"result":{"duration":5685145000,"status":"passed"},"line":17,"name":"user chooses to abandon the question","match":{"location":"gov.uk.kbv.api.stepdefinitions.KbvSteps.userChoosesToAbandonTheQuestion()"},"keyword":"When "},{"result":{"duration":201000,"status":"passed"},"line":18,"name":"user gets status code 200","match":{"arguments":[{"val":"200","offset":22}],"location":"uk.gov.di.ipv.cri.common.library.stepdefinitions.CommonSteps.userGetsStatusCode(int)"},"keyword":"Then "}],"tags":[{"name":"@pre_merge_abandon"}]},{"start_timestamp":"2023-06-14T15:44:32.027Z","line":20,"name":"User abandons second question","description":"","id":"3-out-of-4-strategy.-user-has-2-kbv-questions.-tests-are-run-against-the-kbv-stub.;user-abandons-second-question","type":"scenario","keyword":"Scenario","steps":[{"result":{"duration":831676000,"status":"passed"},"line":21,"name":"user has the test-identity 168 in the form of a signed JWT string","match":{"arguments":[{"val":"168","offset":27}],"location":"uk.gov.di.ipv.cri.common.library.stepdefinitions.CommonSteps.userHasTheTestIdentityInTheFormOfASignedJWTString(int)"},"keyword":"Given "},{"result":{"duration":633741000,"status":"passed"},"line":24,"name":"user sends a POST request to session end point","match":{"location":"uk.gov.di.ipv.cri.common.library.stepdefinitions.CommonSteps.userSendsAPostRequestToSessionEndpoint()"},"keyword":"When "},{"result":{"duration":150000,"status":"passed"},"line":25,"name":"user gets a session-id","match":{"location":"uk.gov.di.ipv.cri.common.library.stepdefinitions.CommonSteps.userGetsASessionId()"},"keyword":"Then "},{"result":{"duration":866324000,"status":"passed"},"line":28,"name":"user sends a GET request to question end point","match":{"location":"gov.uk.kbv.api.stepdefinitions.KbvSteps.user_sends_a_get_request_to_question_end_point()"},"keyword":"When "},{"result":{"duration":153000,"status":"passed"},"line":29,"name":"user gets status code 200","match":{"arguments":[{"val":"200","offset":22}],"location":"uk.gov.di.ipv.cri.common.library.stepdefinitions.CommonSteps.userGetsStatusCode(int)"},"keyword":"Then "},{"result":{"duration":8073212000,"status":"passed"},"line":30,"name":"user answers the question correctly","match":{"location":"gov.uk.kbv.api.stepdefinitions.KbvSteps.userAnswersTheQuestionCorrectly()"},"keyword":"And "},{"result":{"duration":177000,"status":"passed"},"line":31,"name":"user gets status code 200","match":{"arguments":[{"val":"200","offset":22}],"location":"uk.gov.di.ipv.cri.common.library.stepdefinitions.CommonSteps.userGetsStatusCode(int)"},"keyword":"Then "},{"result":{"duration":303755000,"status":"passed"},"line":34,"name":"user sends a GET request to question end point","match":{"location":"gov.uk.kbv.api.stepdefinitions.KbvSteps.user_sends_a_get_request_to_question_end_point()"},"keyword":"When "},{"result":{"duration":810000,"status":"passed"},"line":35,"name":"user gets status code 200","match":{"arguments":[{"val":"200","offset":22}],"location":"uk.gov.di.ipv.cri.common.library.stepdefinitions.CommonSteps.userGetsStatusCode(int)"},"keyword":"Then "},{"result":{"duration":359249000,"status":"passed"},"line":38,"name":"user chooses to abandon the question","match":{"location":"gov.uk.kbv.api.stepdefinitions.KbvSteps.userChoosesToAbandonTheQuestion()"},"keyword":"When "},{"result":{"duration":184000,"status":"passed"},"line":39,"name":"user gets status code 200","match":{"arguments":[{"val":"200","offset":22}],"location":"uk.gov.di.ipv.cri.common.library.stepdefinitions.CommonSteps.userGetsStatusCode(int)"},"keyword":"Then "}],"tags":[{"name":"@pre_merge_abandon"}]}],"name":"3 out of 4 strategy. User has 2 KBV questions. Tests are run against the KBV Stub.","description":"  User chooses to abandon the question during KBV flow","id":"3-out-of-4-strategy.-user-has-2-kbv-questions.-tests-are-run-against-the-kbv-stub.","keyword":"Feature","uri":"file:src/test/resources/features/KbvApiAbandonPath.feature","tags":[{"name":"@pre_merge_abandon","type":"Tag","location":{"line":1,"column":1}}]},{"line":1,"elements":[{"start_timestamp":"2023-06-14T15:44:43.115Z","line":5,"name":"User answers 2 questions correctly","description":"","id":"3-out-of-4-strategy.-user-has-2-kbv-questions.-tests-are-run-against-the-kbv-stub.;user-answers-2-questions-correctly","type":"scenario","keyword":"Scenario","steps":[{"result":{"duration":1192576000,"status":"passed"},"line":6,"name":"user has the test-identity 168 in the form of a signed JWT string","match":{"arguments":[{"val":"168","offset":27}],"location":"uk.gov.di.ipv.cri.common.library.stepdefinitions.CommonSteps.userHasTheTestIdentityInTheFormOfASignedJWTString(int)"},"keyword":"Given "},{"result":{"duration":828769000,"status":"passed"},"line":9,"name":"user sends a POST request to session end point","match":{"location":"uk.gov.di.ipv.cri.common.library.stepdefinitions.CommonSteps.userSendsAPostRequestToSessionEndpoint()"},"keyword":"When "},{"result":{"duration":127000,"status":"passed"},"line":10,"name":"user gets a session-id","match":{"location":"uk.gov.di.ipv.cri.common.library.stepdefinitions.CommonSteps.userGetsASessionId()"},"keyword":"Then "},{"result":{"duration":769498000,"status":"passed"},"line":13,"name":"user sends a GET request to question end point","match":{"location":"gov.uk.kbv.api.stepdefinitions.KbvSteps.user_sends_a_get_request_to_question_end_point()"},"keyword":"When "},{"result":{"duration":183000,"status":"passed"},"line":14,"name":"user gets status code 200","match":{"arguments":[{"val":"200","offset":22}],"location":"uk.gov.di.ipv.cri.common.library.stepdefinitions.CommonSteps.userGetsStatusCode(int)"},"keyword":"Then "},{"result":{"duration":238004000,"status":"passed"},"line":15,"name":"user answers the question correctly","match":{"location":"gov.uk.kbv.api.stepdefinitions.KbvSteps.userAnswersTheQuestionCorrectly()"},"keyword":"And "},{"result":{"duration":173000,"status":"passed"},"line":16,"name":"user gets status code 200","match":{"arguments":[{"val":"200","offset":22}],"location":"uk.gov.di.ipv.cri.common.library.stepdefinitions.CommonSteps.userGetsStatusCode(int)"},"keyword":"Then "},{"result":{"duration":215330000,"status":"passed"},"line":19,"name":"user sends a GET request to question end point","match":{"location":"gov.uk.kbv.api.stepdefinitions.KbvSteps.user_sends_a_get_request_to_question_end_point()"},"keyword":"When "},{"result":{"duration":176000,"status":"passed"},"line":20,"name":"user gets status code 200","match":{"arguments":[{"val":"200","offset":22}],"location":"uk.gov.di.ipv.cri.common.library.stepdefinitions.CommonSteps.userGetsStatusCode(int)"},"keyword":"Then "},{"result":{"duration":3563701000,"status":"passed"},"line":21,"name":"user answers the question correctly","match":{"location":"gov.uk.kbv.api.stepdefinitions.KbvSteps.userAnswersTheQuestionCorrectly()"},"keyword":"And "},{"result":{"duration":194000,"status":"passed"},"line":22,"name":"user gets status code 200","match":{"arguments":[{"val":"200","offset":22}],"location":"uk.gov.di.ipv.cri.common.library.stepdefinitions.CommonSteps.userGetsStatusCode(int)"},"keyword":"Then "},{"result":{"duration":250423000,"status":"passed"},"line":24,"name":"user sends a GET request to question end point when there are no questions left","match":{"location":"gov.uk.kbv.api.stepdefinitions.KbvSteps.userSendsAGETRequestToQuestionEndPointWhenThereAreNoQuestionsLeft()"},"keyword":"When "},{"result":{"duration":166000,"status":"passed"},"line":25,"name":"user gets status code 204","match":{"arguments":[{"val":"204","offset":22}],"location":"uk.gov.di.ipv.cri.common.library.stepdefinitions.CommonSteps.userGetsStatusCode(int)"},"keyword":"Then "},{"result":{"duration":1658874000,"status":"passed"},"line":28,"name":"user sends a GET request to authorization end point","match":{"location":"uk.gov.di.ipv.cri.common.library.stepdefinitions.CommonSteps.userSendsAGetRequestToAuthorizationEndpoint()"},"keyword":"When "},{"result":{"duration":193000,"status":"passed"},"line":29,"name":"user gets status code 200","match":{"arguments":[{"val":"200","offset":22}],"location":"uk.gov.di.ipv.cri.common.library.stepdefinitions.CommonSteps.userGetsStatusCode(int)"},"keyword":"Then "},{"result":{"duration":4180000,"status":"passed"},"line":30,"name":"a valid authorization code is returned in the response","match":{"location":"uk.gov.di.ipv.cri.common.library.stepdefinitions.CommonSteps.aValidAuthorizationCodeIsReturnedInTheResponse()"},"keyword":"And "},{"result":{"duration":2420133000,"status":"passed"},"line":33,"name":"user sends a POST request to token end point","match":{"location":"uk.gov.di.ipv.cri.common.library.stepdefinitions.CommonSteps.userSendsAPostRequestToTokenEndpoint()"},"keyword":"When "},{"result":{"duration":219000,"status":"passed"},"line":34,"name":"user gets status code 200","match":{"arguments":[{"val":"200","offset":22}],"location":"uk.gov.di.ipv.cri.common.library.stepdefinitions.CommonSteps.userGetsStatusCode(int)"},"keyword":"Then "},{"result":{"duration":3059000,"status":"passed"},"line":35,"name":"a valid access token code is returned in the response","match":{"location":"uk.gov.di.ipv.cri.common.library.stepdefinitions.CommonSteps.aValidAccessTokenCodeIsReturnedInTheResponse()"},"keyword":"And "},{"result":{"duration":7896709000,"status":"passed"},"line":38,"name":"user sends a POST request to Credential Issue end point with a valid access token","match":{"location":"gov.uk.kbv.api.stepdefinitions.KbvSteps.user_sends_a_post_request_to_credential_issue_end_point_with_a_valid_access_token()"},"keyword":"When "},{"result":{"duration":159000,"status":"passed"},"line":39,"name":"user gets status code 200","match":{"arguments":[{"val":"200","offset":22}],"location":"uk.gov.di.ipv.cri.common.library.stepdefinitions.CommonSteps.userGetsStatusCode(int)"},"keyword":"Then "},{"result":{"duration":22915000,"status":"passed"},"line":40,"name":"a valid JWT is returned in the response","match":{"location":"gov.uk.kbv.api.stepdefinitions.KbvSteps.aValidJWTIsReturnedInTheResponse()"},"keyword":"And "},{"result":{"duration":591000,"status":"passed"},"line":41,"name":"a verification score of 2 is returned in the response","match":{"arguments":[{"val":"2","offset":24}],"location":"gov.uk.kbv.api.stepdefinitions.KbvSteps.aVerificationScoreIsReturnedInTheResponse(int)"},"keyword":"And "}],"tags":[{"name":"@pre_merge_happy"}]}],"name":"3 out of 4 strategy. User has 2 KBV questions. Tests are run against the KBV Stub.","description":"  User answers the two questions correctly and gets valid JWT from the credential issuer","id":"3-out-of-4-strategy.-user-has-2-kbv-questions.-tests-are-run-against-the-kbv-stub.","keyword":"Feature","uri":"file:src/test/resources/features/KbvApiHappyPath.feature","tags":[]},{"line":1,"elements":[{"start_timestamp":"2023-06-14T15:45:02.199Z","line":5,"name":"User answers 2 questions incorrectly","description":"","id":"3-out-of-4-strategy.-user-has-2-kbv-questions.-tests-are-run-against-the-kbv-stub.;user-answers-2-questions-incorrectly","type":"scenario","keyword":"Scenario","steps":[{"result":{"duration":848567000,"status":"passed"},"line":6,"name":"user has the test-identity 168 in the form of a signed JWT string","match":{"arguments":[{"val":"168","offset":27}],"location":"uk.gov.di.ipv.cri.common.library.stepdefinitions.CommonSteps.userHasTheTestIdentityInTheFormOfASignedJWTString(int)"},"keyword":"Given "},{"result":{"duration":583756000,"status":"passed"},"line":9,"name":"user sends a POST request to session end point","match":{"location":"uk.gov.di.ipv.cri.common.library.stepdefinitions.CommonSteps.userSendsAPostRequestToSessionEndpoint()"},"keyword":"When "},{"result":{"duration":104000,"status":"passed"},"line":10,"name":"user gets a session-id","match":{"location":"uk.gov.di.ipv.cri.common.library.stepdefinitions.CommonSteps.userGetsASessionId()"},"keyword":"Then "},{"result":{"duration":945776000,"status":"passed"},"line":13,"name":"user sends a GET request to question end point","match":{"location":"gov.uk.kbv.api.stepdefinitions.KbvSteps.user_sends_a_get_request_to_question_end_point()"},"keyword":"When "},{"result":{"duration":169000,"status":"passed"},"line":14,"name":"user gets status code 200","match":{"arguments":[{"val":"200","offset":22}],"location":"uk.gov.di.ipv.cri.common.library.stepdefinitions.CommonSteps.userGetsStatusCode(int)"},"keyword":"Then "},{"result":{"duration":315910000,"status":"passed"},"line":15,"name":"user answers the question incorrectly","match":{"location":"gov.uk.kbv.api.stepdefinitions.KbvSteps.user_answers_the_question_incorrectly()"},"keyword":"And "},{"result":{"duration":618000,"status":"passed"},"line":16,"name":"user gets status code 200","match":{"arguments":[{"val":"200","offset":22}],"location":"uk.gov.di.ipv.cri.common.library.stepdefinitions.CommonSteps.userGetsStatusCode(int)"},"keyword":"Then "},{"result":{"duration":223729000,"status":"passed"},"line":19,"name":"user sends a GET request to question end point","match":{"location":"gov.uk.kbv.api.stepdefinitions.KbvSteps.user_sends_a_get_request_to_question_end_point()"},"keyword":"When "},{"result":{"duration":158000,"status":"passed"},"line":20,"name":"user gets status code 200","match":{"arguments":[{"val":"200","offset":22}],"location":"uk.gov.di.ipv.cri.common.library.stepdefinitions.CommonSteps.userGetsStatusCode(int)"},"keyword":"Then "},{"result":{"duration":452335000,"status":"passed"},"line":21,"name":"user answers the question incorrectly","match":{"location":"gov.uk.kbv.api.stepdefinitions.KbvSteps.user_answers_the_question_incorrectly()"},"keyword":"And "},{"result":{"duration":179000,"status":"passed"},"line":22,"name":"user gets status code 200","match":{"arguments":[{"val":"200","offset":22}],"location":"uk.gov.di.ipv.cri.common.library.stepdefinitions.CommonSteps.userGetsStatusCode(int)"},"keyword":"Then "},{"result":{"duration":244639000,"status":"passed"},"line":24,"name":"user sends a GET request to question end point when there are no questions left","match":{"location":"gov.uk.kbv.api.stepdefinitions.KbvSteps.userSendsAGETRequestToQuestionEndPointWhenThereAreNoQuestionsLeft()"},"keyword":"When "},{"result":{"duration":156000,"status":"passed"},"line":25,"name":"user gets status code 204","match":{"arguments":[{"val":"204","offset":22}],"location":"uk.gov.di.ipv.cri.common.library.stepdefinitions.CommonSteps.userGetsStatusCode(int)"},"keyword":"Then "},{"result":{"duration":539580000,"status":"passed"},"line":28,"name":"user sends a GET request to authorization end point","match":{"location":"uk.gov.di.ipv.cri.common.library.stepdefinitions.CommonSteps.userSendsAGetRequestToAuthorizationEndpoint()"},"keyword":"When "},{"result":{"duration":157000,"status":"passed"},"line":29,"name":"user gets status code 200","match":{"arguments":[{"val":"200","offset":22}],"location":"uk.gov.di.ipv.cri.common.library.stepdefinitions.CommonSteps.userGetsStatusCode(int)"},"keyword":"Then "},{"result":{"duration":268000,"status":"passed"},"line":30,"name":"a valid authorization code is returned in the response","match":{"location":"uk.gov.di.ipv.cri.common.library.stepdefinitions.CommonSteps.aValidAuthorizationCodeIsReturnedInTheResponse()"},"keyword":"And "},{"result":{"duration":938833000,"status":"passed"},"line":33,"name":"user sends a POST request to token end point","match":{"location":"uk.gov.di.ipv.cri.common.library.stepdefinitions.CommonSteps.userSendsAPostRequestToTokenEndpoint()"},"keyword":"When "},{"result":{"duration":160000,"status":"passed"},"line":34,"name":"user gets status code 200","match":{"arguments":[{"val":"200","offset":22}],"location":"uk.gov.di.ipv.cri.common.library.stepdefinitions.CommonSteps.userGetsStatusCode(int)"},"keyword":"Then "},{"result":{"duration":198000,"status":"passed"},"line":35,"name":"a valid access token code is returned in the response","match":{"location":"uk.gov.di.ipv.cri.common.library.stepdefinitions.CommonSteps.aValidAccessTokenCodeIsReturnedInTheResponse()"},"keyword":"And "},{"result":{"duration":941762000,"status":"passed"},"line":38,"name":"user sends a POST request to Credential Issue end point with a valid access token","match":{"location":"gov.uk.kbv.api.stepdefinitions.KbvSteps.user_sends_a_post_request_to_credential_issue_end_point_with_a_valid_access_token()"},"keyword":"When "},{"result":{"duration":162000,"status":"passed"},"line":39,"name":"user gets status code 200","match":{"arguments":[{"val":"200","offset":22}],"location":"uk.gov.di.ipv.cri.common.library.stepdefinitions.CommonSteps.userGetsStatusCode(int)"},"keyword":"Then "},{"result":{"duration":794000,"status":"passed"},"line":40,"name":"a verification score of 0 is returned in the response","match":{"arguments":[{"val":"0","offset":24}],"location":"gov.uk.kbv.api.stepdefinitions.KbvSteps.aVerificationScoreIsReturnedInTheResponse(int)"},"keyword":"And "}],"tags":[{"name":"@pre_merge_unhappy"}]}],"name":"3 out of 4 strategy. User has 2 KBV questions. Tests are run against the KBV Stub.","description":"  User answers the two questions incorrectly and fails.","id":"3-out-of-4-strategy.-user-has-2-kbv-questions.-tests-are-run-against-the-kbv-stub.","keyword":"Feature","uri":"file:src/test/resources/features/KbvApiUnhappyPath.feature","tags":[]}]